sabctools/__init__.py
sabctools/py.typed
sabctools/sabctools.cpython-314-aarch64-linux-musl.so
sabctools/sabctools.pyi
sabctools.libs/libgcc_s-2d945d6c.so.1
sabctools.libs/libstdc++-85f2cd6d.so.6.0.33
sabctools-9.3.1.dist-info/METADATA
sabctools-9.3.1.dist-info/WHEEL
sabctools-9.3.1.dist-info/top_level.txt
sabctools-9.3.1.dist-info/RECORD
sabctools-9.3.1.dist-info/licenses/LICENSE.md
sabctools-9.3.1.dist-info/sboms/auditwheel.cdx.json
