Metadata-Version: 2.4
Name: sabctools
Version: 9.3.1
Summary: C implementations of functions for use within SABnzbd
Author-email: Safihre <safihre@sabnzbd.org>
License-Expression: GPL-2.0-or-later
Project-URL: Homepage, https://github.com/sabnzbd/sabctools/
Classifier: Programming Language :: Python
Classifier: Programming Language :: Python :: 3 :: Only
Classifier: Programming Language :: C
Classifier: Operating System :: Microsoft :: Windows
Classifier: Operating System :: Unix
Classifier: Operating System :: MacOS
Classifier: Development Status :: 5 - Production/Stable
Classifier: Environment :: Plugins
Classifier: Topic :: Software Development :: Libraries :: Python Modules
Classifier: Topic :: Communications :: Usenet News
Requires-Python: >=3.9
License-File: LICENSE.md
Dynamic: license-file
